movefile_restart/__init__.py
movefile_restart/__main__.py
movefile_restart/main.py
movefile_restart/movefile_restart.py
movefile_restart-1.0.1.dist-info/LICENSE
movefile_restart-1.0.1.dist-info/METADATA
movefile_restart-1.0.1.dist-info/WHEEL
movefile_restart-1.0.1.dist-info/top_level.txt
movefile_restart-1.0.1.dist-info/RECORD
