Metadata-Version: 2.1
Name: movefile-restart
Version: 1.0.1
Summary: A small library for Windows to queue files to be moved, deleted, or renamed on reboot.
Home-page: https://github.com/hammy3502/python-movefile-restart
Author: hammy3502
Author-email: hammy275@gmail.com
License: UNKNOWN
Platform: UNKNOWN
Classifier: Programming Language :: Python :: 3
Classifier: License :: OSI Approved :: MIT License
Classifier: Operating System :: Microsoft :: Windows
Requires-Python: >=3.6
